masterframework/__init__.py
masterframework/data_loader.py
masterframework/experiment_runner.py
masterframework/augmentation/augmentation.py
masterframework/augmentation/generator.py
masterframework/augmentation/rag.py
masterframework/evaluation/metrics.py
masterframework/evaluation/result_parser.py
masterframework/evaluation/security_analyzer.py
masterframework/models/api_providers.py
masterframework/models/hf_provider.py
masterframework/models/local_provider.py
masterframework/models/model_provider.py
masterframework/utils/code_utils.py
masterframework/utils/dataset_generator.py
masterframework-0.5.0.dist-info/METADATA
masterframework-0.5.0.dist-info/WHEEL
masterframework-0.5.0.dist-info/top_level.txt
masterframework-0.5.0.dist-info/RECORD
