Metadata-Version: 2.4
Name: masterframework
Version: 0.5.0
Summary: Add your description here
Requires-Python: >=3.9
